{"nodes": [{"id": "tests_backend_test_alpha_audit_py", "label": "test_alpha_audit.py", "file_type": "code", "source_file": "tests/backend/test_alpha_audit.py", "source_location": "L1"}, {"id": "test_alpha_audit_test_agent_alpha_audit_flow", "label": "test_agent_alpha_audit_flow()", "file_type": "code", "source_file": "tests/backend/test_alpha_audit.py", "source_location": "L11"}, {"id": "test_alpha_audit_rationale_12", "label": "Verify that agent runs result in alpha performance tracking with specialist brea", "file_type": "rationale", "source_file": "tests/backend/test_alpha_audit.py", "source_location": "L12"}], "edges": [{"source": "tests_backend_test_alpha_audit_py", "target": "pytest", "relation": "imports", "confidence": "EXTRACTED", "source_file": "tests/backend/test_alpha_audit.py", "source_location": "L1", "weight": 1.0}, {"source": "tests_backend_test_alpha_audit_py", "target": "asyncio", "relation": "imports", "confidence": "EXTRACTED", "source_file": "tests/backend/test_alpha_audit.py", "source_location": "L2", "weight": 1.0}, {"source": "tests_backend_test_alpha_audit_py", "target": "pandas", "relation": "imports", "confidence": "EXTRACTED", "source_file": "tests/backend/test_alpha_audit.py", "source_location": "L3", "weight": 1.0}, {"source": "tests_backend_test_alpha_audit_py", "target": "datetime", "relation": "imports_from", "confidence": "EXTRACTED", "source_file": "tests/backend/test_alpha_audit.py", "source_location": "L4", "weight": 1.0}, {"source": "tests_backend_test_alpha_audit_py", "target": "analytics_db", "relation": "imports_from", "confidence": "EXTRACTED", "source_file": "tests/backend/test_alpha_audit.py", "source_location": "L5", "weight": 1.0}, {"source": "tests_backend_test_alpha_audit_py", "target": "agents_orchestrator_agent", "relation": "imports_from", "confidence": "EXTRACTED", "source_file": "tests/backend/test_alpha_audit.py", "source_location": "L6", "weight": 1.0}, {"source": "tests_backend_test_alpha_audit_py", "target": "unittest_mock", "relation": "imports_from", "confidence": "EXTRACTED", "source_file": "tests/backend/test_alpha_audit.py", "source_location": "L7", "weight": 1.0}, {"source": "tests_backend_test_alpha_audit_py", "target": "test_alpha_audit_test_agent_alpha_audit_flow", "relation": "contains", "confidence": "EXTRACTED", "source_file": "tests/backend/test_alpha_audit.py", "source_location": "L11", "weight": 1.0}, {"source": "test_alpha_audit_rationale_12", "target": "test_alpha_audit_test_agent_alpha_audit_flow", "relation": "rationale_for", "confidence": "EXTRACTED", "source_file": "tests/backend/test_alpha_audit.py", "source_location": "L12", "weight": 1.0}]}