{"nodes": [{"id": "backend_utils_process_guard_py", "label": "process_guard.py", "file_type": "code", "source_file": "backend/utils/process_guard.py", "source_location": "L1"}, {"id": "process_guard_start_parent_watchdog", "label": "start_parent_watchdog()", "file_type": "code", "source_file": "backend/utils/process_guard.py", "source_location": "L18"}, {"id": "process_guard_rationale_1", "label": "Process Guard Utility Ensures that a process exits if its parent process dies or", "file_type": "rationale", "source_file": "backend/utils/process_guard.py", "source_location": "L1"}, {"id": "process_guard_rationale_19", "label": "Starts a daemon thread that monitors the parent process.     If the parent proce", "file_type": "rationale", "source_file": "backend/utils/process_guard.py", "source_location": "L19"}], "edges": [{"source": "backend_utils_process_guard_py", "target": "os", "relation": "imports", "confidence": "EXTRACTED", "source_file": "backend/utils/process_guard.py", "source_location": "L6", "weight": 1.0}, {"source": "backend_utils_process_guard_py", "target": "sys", "relation": "imports", "confidence": "EXTRACTED", "source_file": "backend/utils/process_guard.py", "source_location": "L7", "weight": 1.0}, {"source": "backend_utils_process_guard_py", "target": "time", "relation": "imports", "confidence": "EXTRACTED", "source_file": "backend/utils/process_guard.py", "source_location": "L8", "weight": 1.0}, {"source": "backend_utils_process_guard_py", "target": "threading", "relation": "imports", "confidence": "EXTRACTED", "source_file": "backend/utils/process_guard.py", "source_location": "L9", "weight": 1.0}, {"source": "backend_utils_process_guard_py", "target": "logging", "relation": "imports", "confidence": "EXTRACTED", "source_file": "backend/utils/process_guard.py", "source_location": "L10", "weight": 1.0}, {"source": "backend_utils_process_guard_py", "target": "process_guard_start_parent_watchdog", "relation": "contains", "confidence": "EXTRACTED", "source_file": "backend/utils/process_guard.py", "source_location": "L18", "weight": 1.0}, {"source": "process_guard_rationale_1", "target": "backend_utils_process_guard_py", "relation": "rationale_for", "confidence": "EXTRACTED", "source_file": "backend/utils/process_guard.py", "source_location": "L1", "weight": 1.0}, {"source": "process_guard_rationale_19", "target": "process_guard_start_parent_watchdog", "relation": "rationale_for", "confidence": "EXTRACTED", "source_file": "backend/utils/process_guard.py", "source_location": "L19", "weight": 1.0}]}