{"nodes": [{"id": "backend_utils_safe_python_py", "label": "safe_python.py", "file_type": "code", "source_file": "backend/utils/safe_python.py", "source_location": "L1"}, {"id": "safe_python_safe_range", "label": "safe_range()", "file_type": "code", "source_file": "backend/utils/safe_python.py", "source_location": "L88"}, {"id": "safe_python_safe_pow", "label": "safe_pow()", "file_type": "code", "source_file": "backend/utils/safe_python.py", "source_location": "L95"}, {"id": "safe_python_safepythonexecutor", "label": "SafePythonExecutor", "file_type": "code", "source_file": "backend/utils/safe_python.py", "source_location": "L109"}, {"id": "safe_python_safepythonexecutor_init", "label": ".__init__()", "file_type": "code", "source_file": "backend/utils/safe_python.py", "source_location": "L119"}, {"id": "safe_python_safepythonexecutor_prepare_safe_modules", "label": "._prepare_safe_modules()", "file_type": "code", "source_file": "backend/utils/safe_python.py", "source_location": "L124"}, {"id": "safe_python_safepythonexecutor_validate_code", "label": "._validate_code()", "file_type": "code", "source_file": "backend/utils/safe_python.py", "source_location": "L133"}, {"id": "safe_python_safepythonexecutor_execute", "label": ".execute()", "file_type": "code", "source_file": "backend/utils/safe_python.py", "source_location": "L172"}, {"id": "safe_python_get_safe_executor", "label": "get_safe_executor()", "file_type": "code", "source_file": "backend/utils/safe_python.py", "source_location": "L282"}, {"id": "safe_python_run_safe_python", "label": "run_safe_python()", "file_type": "code", "source_file": "backend/utils/safe_python.py", "source_location": "L291"}, {"id": "safe_python_rationale_1", "label": "Safe Python Executor - Sandboxed Python execution for Coordinator Agent  Provide", "file_type": "rationale", "source_file": "backend/utils/safe_python.py", "source_location": "L1"}, {"id": "safe_python_rationale_89", "label": "Restricted range to prevent memory exhaustion.", "file_type": "rationale", "source_file": "backend/utils/safe_python.py", "source_location": "L89"}, {"id": "safe_python_rationale_96", "label": "Restricted power to prevent CPU exhaustion.", "file_type": "rationale", "source_file": "backend/utils/safe_python.py", "source_location": "L96"}, {"id": "safe_python_rationale_110", "label": "Executes Python code in a restricted sandbox.          Designed for the Coordina", "file_type": "rationale", "source_file": "backend/utils/safe_python.py", "source_location": "L110"}, {"id": "safe_python_rationale_125", "label": "Pre-import allowed modules for the sandbox.", "file_type": "rationale", "source_file": "backend/utils/safe_python.py", "source_location": "L125"}, {"id": "safe_python_rationale_134", "label": "Static analysis to block dangerous patterns before execution.                  R", "file_type": "rationale", "source_file": "backend/utils/safe_python.py", "source_location": "L134"}, {"id": "safe_python_rationale_173", "label": "Execute Python code in the sandbox.                  Args:             code: Pyt", "file_type": "rationale", "source_file": "backend/utils/safe_python.py", "source_location": "L173"}, {"id": "safe_python_rationale_283", "label": "Get or create the global SafePythonExecutor instance.", "file_type": "rationale", "source_file": "backend/utils/safe_python.py", "source_location": "L283"}, {"id": "safe_python_rationale_292", "label": "Execute Python code safely in the sandbox.          Example:         result = ru", "file_type": "rationale", "source_file": "backend/utils/safe_python.py", "source_location": "L292"}], "edges": [{"source": "backend_utils_safe_python_py", "target": "ast", "relation": "imports", "confidence": "EXTRACTED", "source_file": "backend/utils/safe_python.py", "source_location": "L15", "weight": 1.0}, {"source": "backend_utils_safe_python_py", "target": "sys", "relation": "imports", "confidence": "EXTRACTED", "source_file": "backend/utils/safe_python.py", "source_location": "L16", "weight": 1.0}, {"source": "backend_utils_safe_python_py", "target": "logging", "relation": "imports", "confidence": "EXTRACTED", "source_file": "backend/utils/safe_python.py", "source_location": "L17", "weight": 1.0}, {"source": "backend_utils_safe_python_py", "target": "typing", "relation": "imports_from", "confidence": "EXTRACTED", "source_file": "backend/utils/safe_python.py", "source_location": "L18", "weight": 1.0}, {"source": "backend_utils_safe_python_py", "target": "io", "relation": "imports_from", "confidence": "EXTRACTED", "source_file": "backend/utils/safe_python.py", "source_location": "L19", "weight": 1.0}, {"source": "backend_utils_safe_python_py", "target": "safe_python_safe_range", "relation": "contains", "confidence": "EXTRACTED", "source_file": "backend/utils/safe_python.py", "source_location": "L88", "weight": 1.0}, {"source": "backend_utils_safe_python_py", "target": "safe_python_safe_pow", "relation": "contains", "confidence": "EXTRACTED", "source_file": "backend/utils/safe_python.py", "source_location": "L95", "weight": 1.0}, {"source": "backend_utils_safe_python_py", "target": "safe_python_safepythonexecutor", "relation": "contains", "confidence": "EXTRACTED", "source_file": "backend/utils/safe_python.py", "source_location": "L109", "weight": 1.0}, {"source": "safe_python_safepythonexecutor", "target": "safe_python_safepythonexecutor_init", "relation": "method", "confidence": "EXTRACTED", "source_file": "backend/utils/safe_python.py", "source_location": "L119", "weight": 1.0}, {"source": "safe_python_safepythonexecutor", "target": "safe_python_safepythonexecutor_prepare_safe_modules", "relation": "method", "confidence": "EXTRACTED", "source_file": "backend/utils/safe_python.py", "source_location": "L124", "weight": 1.0}, {"source": "safe_python_safepythonexecutor", "target": "safe_python_safepythonexecutor_validate_code", "relation": "method", "confidence": "EXTRACTED", "source_file": "backend/utils/safe_python.py", "source_location": "L133", "weight": 1.0}, {"source": "safe_python_safepythonexecutor", "target": "safe_python_safepythonexecutor_execute", "relation": "method", "confidence": "EXTRACTED", "source_file": "backend/utils/safe_python.py", "source_location": "L172", "weight": 1.0}, {"source": "backend_utils_safe_python_py", "target": "safe_python_get_safe_executor", "relation": "contains", "confidence": "EXTRACTED", "source_file": "backend/utils/safe_python.py", "source_location": "L282", "weight": 1.0}, {"source": "backend_utils_safe_python_py", "target": "safe_python_run_safe_python", "relation": "contains", "confidence": "EXTRACTED", "source_file": "backend/utils/safe_python.py", "source_location": "L291", "weight": 1.0}, {"source": "safe_python_safepythonexecutor_init", "target": "safe_python_safepythonexecutor_prepare_safe_modules", "relation": "calls", "confidence": "EXTRACTED", "source_file": "backend/utils/safe_python.py", "source_location": "L122", "weight": 1.0}, {"source": "safe_python_safepythonexecutor_execute", "target": "safe_python_safepythonexecutor_validate_code", "relation": "calls", "confidence": "EXTRACTED", "source_file": "backend/utils/safe_python.py", "source_location": "L189", "weight": 1.0}, {"source": "safe_python_get_safe_executor", "target": "safe_python_safepythonexecutor", "relation": "calls", "confidence": "EXTRACTED", "source_file": "backend/utils/safe_python.py", "source_location": "L286", "weight": 1.0}, {"source": "safe_python_run_safe_python", "target": "safe_python_safepythonexecutor_execute", "relation": "calls", "confidence": "EXTRACTED", "source_file": "backend/utils/safe_python.py", "source_location": "L309", "weight": 1.0}, {"source": "safe_python_run_safe_python", "target": "safe_python_get_safe_executor", "relation": "calls", "confidence": "EXTRACTED", "source_file": "backend/utils/safe_python.py", "source_location": "L309", "weight": 1.0}, {"source": "safe_python_rationale_1", "target": "backend_utils_safe_python_py", "relation": "rationale_for", "confidence": "EXTRACTED", "source_file": "backend/utils/safe_python.py", "source_location": "L1", "weight": 1.0}, {"source": "safe_python_rationale_89", "target": "safe_python_safe_range", "relation": "rationale_for", "confidence": "EXTRACTED", "source_file": "backend/utils/safe_python.py", "source_location": "L89", "weight": 1.0}, {"source": "safe_python_rationale_96", "target": "safe_python_safe_pow", "relation": "rationale_for", "confidence": "EXTRACTED", "source_file": "backend/utils/safe_python.py", "source_location": "L96", "weight": 1.0}, {"source": "safe_python_rationale_110", "target": "safe_python_safepythonexecutor", "relation": "rationale_for", "confidence": "EXTRACTED", "source_file": "backend/utils/safe_python.py", "source_location": "L110", "weight": 1.0}, {"source": "safe_python_rationale_125", "target": "safe_python_safepythonexecutor_prepare_safe_modules", "relation": "rationale_for", "confidence": "EXTRACTED", "source_file": "backend/utils/safe_python.py", "source_location": "L125", "weight": 1.0}, {"source": "safe_python_rationale_134", "target": "safe_python_safepythonexecutor_validate_code", "relation": "rationale_for", "confidence": "EXTRACTED", "source_file": "backend/utils/safe_python.py", "source_location": "L134", "weight": 1.0}, {"source": "safe_python_rationale_173", "target": "safe_python_safepythonexecutor_execute", "relation": "rationale_for", "confidence": "EXTRACTED", "source_file": "backend/utils/safe_python.py", "source_location": "L173", "weight": 1.0}, {"source": "safe_python_rationale_283", "target": "safe_python_get_safe_executor", "relation": "rationale_for", "confidence": "EXTRACTED", "source_file": "backend/utils/safe_python.py", "source_location": "L283", "weight": 1.0}, {"source": "safe_python_rationale_292", "target": "safe_python_run_safe_python", "relation": "rationale_for", "confidence": "EXTRACTED", "source_file": "backend/utils/safe_python.py", "source_location": "L292", "weight": 1.0}]}